{"py/object": "javalang.tree.CompilationUnit", "package": null, "imports": [], "types": [{"py/object": "javalang.tree.ClassDeclaration", "modifiers": {"py/set": ["public"]}, "annotations": [], "documentation": "/**\n *\n * @author 020A6EC1A4D0C5BDB29FF826A462DA1C5D88CF08B60A4744AFFD95C61A0C3C7E\n */", "name": "Main", "body": [{"py/object": "javalang.tree.FieldDeclaration", "documentation": null, "modifiers": {"py/set": ["static", "private"]}, "annotations": [], "type": {"py/object": "javalang.tree.BasicType", "name": "int", "dimensions": []}, "declarators": [{"py/object": "javalang.tree.VariableDeclarator", "name": "mile", "dimensions": [], "initializer": null}], "_position": {"py/object": "javalang.tokenizer.Position", "py/newargs": {"py/tuple": [8, 20]}, "py/seq": [8, 20]}}, {"py/object": "javalang.tree.MethodDeclaration", "documentation": null, "modifiers": {"py/set": ["static", "public"]}, "annotations": [], "type_parameters": null, "return_type": null, "name": "main", "parameters": [{"py/object": "javalang.tree.FormalParameter", "modifiers": {"py/set": []}, "annotations": [], "type": {"py/object": "javalang.tree.ReferenceType", "name": "String", "dimensions": [null], "arguments": null, "sub_type": null}, "name": "args", "varargs": false, "_position": {"py/object": "javalang.tokenizer.Position", "py/newargs": {"py/tuple": [9, 29]}, "py/seq": [9, 29]}}], "throws": null, "body": [{"py/object": "javalang.tree.StatementExpression", "label": null, "expression": {"py/object": "javalang.tree.Assignment", "expressionl": {"py/object": "javalang.tree.MemberReference", "prefix_operators": [], "postfix_operators": [], "qualifier": "", "selectors": [], "member": "mile", "_position": {"py/object": "javalang.tokenizer.Position", "py/newargs": {"py/tuple": [10, 9]}, "py/seq": [10, 9]}}, "value": {"py/object": "javalang.tree.Literal", "prefix_operators": [], "postfix_operators": [], "qualifier": null, "selectors": [], "value": "1", "_position": {"py/object": "javalang.tokenizer.Position", "py/newargs": {"py/tuple": [10, 16]}, "py/seq": [10, 16]}}, "type": "="}, "_position": {"py/id": 29}}, {"py/object": "javalang.tree.StatementExpression", "label": null, "expression": {"py/object": "javalang.tree.MethodInvocation", "prefix_operators": [], "postfix_operators": [], "qualifier": "System.out", "selectors": [], "type_arguments": null, "arguments": [{"py/object": "javalang.tree.Literal", "prefix_operators": [], "postfix_operators": [], "qualifier": null, "selectors": [], "value": "\"Miles\\t\\tKilometers\"", "_position": {"py/object": "javalang.tokenizer.Position", "py/newargs": {"py/tuple": [11, 28]}, "py/seq": [11, 28]}}], "member": "println", "_position": {"py/object": "javalang.tokenizer.Position", "py/newargs": {"py/tuple": [11, 9]}, "py/seq": [11, 9]}}, "_position": {"py/id": 46}}, {"py/object": "javalang.tree.StatementExpression", "label": null, "expression": {"py/object": "javalang.tree.MethodInvocation", "prefix_operators": [], "postfix_operators": [], "qualifier": "System.out", "selectors": [], "type_arguments": null, "arguments": [{"py/object": "javalang.tree.Literal", "prefix_operators": [], "postfix_operators": [], "qualifier": null, "selectors": [], "value": "\"-------------------------------\"", "_position": {"py/object": "javalang.tokenizer.Position", "py/newargs": {"py/tuple": [12, 28]}, "py/seq": [12, 28]}}], "member": "println", "_position": {"py/object": "javalang.tokenizer.Position", "py/newargs": {"py/tuple": [12, 9]}, "py/seq": [12, 9]}}, "_position": {"py/id": 58}}, {"py/object": "javalang.tree.StatementExpression", "label": null, "expression": {"py/object": "javalang.tree.MethodInvocation", "prefix_operators": [], "postfix_operators": [], "qualifier": "", "selectors": [], "type_arguments": null, "arguments": [], "member": "loops", "_position": {"py/object": "javalang.tokenizer.Position", "py/newargs": {"py/tuple": [13, 9]}, "py/seq": [13, 9]}}, "_position": {"py/id": 65}}], "_position": {"py/object": "javalang.tokenizer.Position", "py/newargs": {"py/tuple": [9, 19]}, "py/seq": [9, 19]}}, {"py/object": "javalang.tree.MethodDeclaration", "documentation": null, "modifiers": {"py/set": ["static", "public"]}, "annotations": [], "type_parameters": null, "return_type": null, "name": "loops", "parameters": [], "throws": null, "body": [{"py/object": "javalang.tree.ForStatement", "label": null, "control": {"py/object": "javalang.tree.ForControl", "init": {"py/object": "javalang.tree.VariableDeclaration", "modifiers": {"py/set": []}, "annotations": [], "type": {"py/object": "javalang.tree.BasicType", "name": "int", "dimensions": []}, "declarators": [{"py/object": "javalang.tree.VariableDeclarator", "name": "i", "dimensions": null, "initializer": {"py/object": "javalang.tree.Literal", "prefix_operators": [], "postfix_operators": [], "qualifier": null, "selectors": [], "value": "10", "_position": {"py/object": "javalang.tokenizer.Position", "py/newargs": {"py/tuple": [18, 22]}, "py/seq": [18, 22]}}}]}, "condition": {"py/object": "javalang.tree.BinaryOperation", "operator": ">", "operandl": {"py/object": "javalang.tree.MemberReference", "prefix_operators": [], "postfix_operators": [], "qualifier": "", "selectors": [], "member": "i", "_position": {"py/object": "javalang.tokenizer.Position", "py/newargs": {"py/tuple": [18, 26]}, "py/seq": [18, 26]}}, "operandr": {"py/object": "javalang.tree.Literal", "prefix_operators": [], "postfix_operators": [], "qualifier": null, "selectors": [], "value": "0", "_position": {"py/object": "javalang.tokenizer.Position", "py/newargs": {"py/tuple": [18, 30]}, "py/seq": [18, 30]}}}, "update": [{"py/object": "javalang.tree.MemberReference", "prefix_operators": [], "postfix_operators": ["--"], "qualifier": "", "selectors": [], "member": "i", "_position": {"py/object": "javalang.tokenizer.Position", "py/newargs": {"py/tuple": [18, 33]}, "py/seq": [18, 33]}}]}, "body": {"py/object": "javalang.tree.BlockStatement", "label": null, "statements": [{"py/object": "javalang.tree.StatementExpression", "label": null, "expression": {"py/object": "javalang.tree.MethodInvocation", "prefix_operators": [], "postfix_operators": [], "qualifier": "System.out", "selectors": [], "type_arguments": null, "arguments": [{"py/object": "javalang.tree.BinaryOperation", "operator": "+", "operandl": {"py/object": "javalang.tree.BinaryOperation", "operator": "+", "operandl": {"py/object": "javalang.tree.MemberReference", "prefix_operators": [], "postfix_operators": [], "qualifier": "", "selectors": [], "member": "mile", "_position": {"py/object": "javalang.tokenizer.Position", "py/newargs": {"py/tuple": [19, 32]}, "py/seq": [19, 32]}}, "operandr": {"py/object": "javalang.tree.Literal", "prefix_operators": [], "postfix_operators": [], "qualifier": null, "selectors": [], "value": "\"\\t\\t\"", "_position": {"py/object": "javalang.tokenizer.Position", "py/newargs": {"py/tuple": [19, 39]}, "py/seq": [19, 39]}}}, "operandr": {"py/object": "javalang.tree.BinaryOperation", "operator": "*", "operandl": {"py/object": "javalang.tree.MemberReference", "prefix_operators": [], "postfix_operators": [], "qualifier": "", "selectors": [], "member": "mile", "_position": {"py/object": "javalang.tokenizer.Position", "py/newargs": {"py/tuple": [19, 48]}, "py/seq": [19, 48]}}, "operandr": {"py/object": "javalang.tree.Literal", "prefix_operators": [], "postfix_operators": [], "qualifier": null, "selectors": [], "value": "1.609", "_position": {"py/object": "javalang.tokenizer.Position", "py/newargs": {"py/tuple": [19, 55]}, "py/seq": [19, 55]}}}}], "member": "println", "_position": {"py/object": "javalang.tokenizer.Position", "py/newargs": {"py/tuple": [19, 13]}, "py/seq": [19, 13]}}, "_position": {"py/id": 132}}, {"py/object": "javalang.tree.StatementExpression", "label": null, "expression": {"py/object": "javalang.tree.MemberReference", "prefix_operators": [], "postfix_operators": ["++"], "qualifier": "", "selectors": [], "member": "mile", "_position": {"py/object": "javalang.tokenizer.Position", "py/newargs": {"py/tuple": [20, 17]}, "py/seq": [20, 17]}}, "_position": {"py/id": 138}}], "_position": {"py/object": "javalang.tokenizer.Position", "py/newargs": {"py/tuple": [18, 38]}, "py/seq": [18, 38]}}, "_position": {"py/object": "javalang.tokenizer.Position", "py/newargs": {"py/tuple": [18, 9]}, "py/seq": [18, 9]}}], "_position": {"py/object": "javalang.tokenizer.Position", "py/newargs": {"py/tuple": [16, 19]}, "py/seq": [16, 19]}}], "type_parameters": null, "extends": null, "implements": null, "_position": {"py/object": "javalang.tokenizer.Position", "py/newargs": {"py/tuple": [7, 8]}, "py/seq": [7, 8]}}]}