{"py/object": "javalang.tree.CompilationUnit", "package": null, "imports": [], "types": [{"py/object": "javalang.tree.ClassDeclaration", "modifiers": {"py/set": ["public"]}, "annotations": [], "documentation": "/**\n *\n * @author FD8DBE9073AFCC0504CD6901E1091CAD\n */", "name": "Level4", "body": [{"py/object": "javalang.tree.MethodDeclaration", "documentation": null, "modifiers": {"py/set": ["static", "public"]}, "annotations": [], "type_parameters": null, "return_type": null, "name": "main", "parameters": [{"py/object": "javalang.tree.FormalParameter", "modifiers": {"py/set": []}, "annotations": [], "type": {"py/object": "javalang.tree.ReferenceType", "name": "String", "dimensions": [null], "arguments": null, "sub_type": null}, "name": "args", "varargs": false, "_position": {"py/object": "javalang.tokenizer.Position", "py/newargs": {"py/tuple": [13, 29]}, "py/seq": [13, 29]}}], "throws": null, "body": [{"py/object": "javalang.tree.LocalVariableDeclaration", "modifiers": {"py/set": []}, "annotations": [], "type": {"py/object": "javalang.tree.ReferenceType", "name": "java", "dimensions": [], "arguments": null, "sub_type": {"py/object": "javalang.tree.ReferenceType", "name": "util", "dimensions": null, "arguments": null, "sub_type": {"py/object": "javalang.tree.ReferenceType", "name": "Scanner", "dimensions": null, "arguments": null, "sub_type": null}}}, "declarators": [{"py/object": "javalang.tree.VariableDeclarator", "name": "masukkan", "dimensions": [], "initializer": {"py/object": "javalang.tree.ClassCreator", "prefix_operators": [], "postfix_operators": [], "qualifier": null, "selectors": [], "type": {"py/object": "javalang.tree.ReferenceType", "name": "java", "dimensions": null, "arguments": null, "sub_type": {"py/object": "javalang.tree.ReferenceType", "name": "util", "dimensions": null, "arguments": null, "sub_type": {"py/object": "javalang.tree.ReferenceType", "name": "Scanner", "dimensions": null, "arguments": null, "sub_type": null}}}, "constructor_type_arguments": null, "arguments": [{"py/object": "javalang.tree.MemberReference", "prefix_operators": [], "postfix_operators": [], "qualifier": "System", "selectors": [], "member": "in", "_position": {"py/object": "javalang.tokenizer.Position", "py/newargs": {"py/tuple": [14, 60]}, "py/seq": [14, 60]}}], "body": null}}], "_position": {"py/object": "javalang.tokenizer.Position", "py/newargs": {"py/tuple": [14, 9]}, "py/seq": [14, 9]}}, {"py/object": "javalang.tree.LocalVariableDeclaration", "modifiers": {"py/set": []}, "annotations": [], "type": {"py/object": "javalang.tree.BasicType", "name": "int", "dimensions": []}, "declarators": [{"py/object": "javalang.tree.VariableDeclarator", "name": "number", "dimensions": [], "initializer": null}], "_position": {"py/object": "javalang.tokenizer.Position", "py/newargs": {"py/tuple": [15, 9]}, "py/seq": [15, 9]}}, {"py/object": "javalang.tree.LocalVariableDeclaration", "modifiers": {"py/set": []}, "annotations": [], "type": {"py/object": "javalang.tree.BasicType", "name": "int", "dimensions": []}, "declarators": [{"py/object": "javalang.tree.VariableDeclarator", "name": "sisaBagi", "dimensions": [], "initializer": null}], "_position": {"py/object": "javalang.tokenizer.Position", "py/newargs": {"py/tuple": [16, 9]}, "py/seq": [16, 9]}}, {"py/object": "javalang.tree.StatementExpression", "label": null, "expression": {"py/object": "javalang.tree.MethodInvocation", "prefix_operators": [], "postfix_operators": [], "qualifier": "System.out", "selectors": [], "type_arguments": null, "arguments": [{"py/object": "javalang.tree.Literal", "prefix_operators": [], "postfix_operators": [], "qualifier": null, "selectors": [], "value": "\"Enter an integer: \"", "_position": {"py/object": "javalang.tokenizer.Position", "py/newargs": {"py/tuple": [18, 26]}, "py/seq": [18, 26]}}], "member": "print", "_position": {"py/object": "javalang.tokenizer.Position", "py/newargs": {"py/tuple": [18, 9]}, "py/seq": [18, 9]}}, "_position": {"py/id": 65}}, {"py/object": "javalang.tree.StatementExpression", "label": null, "expression": {"py/object": "javalang.tree.Assignment", "expressionl": {"py/object": "javalang.tree.MemberReference", "prefix_operators": [], "postfix_operators": [], "qualifier": "", "selectors": [], "member": "number", "_position": {"py/object": "javalang.tokenizer.Position", "py/newargs": {"py/tuple": [19, 9]}, "py/seq": [19, 9]}}, "value": {"py/object": "javalang.tree.MethodInvocation", "prefix_operators": [], "postfix_operators": [], "qualifier": "masukkan", "selectors": [], "type_arguments": null, "arguments": [], "member": "nextInt", "_position": {"py/object": "javalang.tokenizer.Position", "py/newargs": {"py/tuple": [19, 18]}, "py/seq": [19, 18]}}, "type": "="}, "_position": {"py/id": 72}}, {"py/object": "javalang.tree.WhileStatement", "label": null, "condition": {"py/object": "javalang.tree.BinaryOperation", "operator": "!=", "operandl": {"py/object": "javalang.tree.MemberReference", "prefix_operators": [], "postfix_operators": [], "qualifier": "", "selectors": [], "member": "number", "_position": {"py/object": "javalang.tokenizer.Position", "py/newargs": {"py/tuple": [21, 16]}, "py/seq": [21, 16]}}, "operandr": {"py/object": "javalang.tree.Literal", "prefix_operators": [], "postfix_operators": [], "qualifier": null, "selectors": [], "value": "0", "_position": {"py/object": "javalang.tokenizer.Position", "py/newargs": {"py/tuple": [21, 26]}, "py/seq": [21, 26]}}}, "body": {"py/object": "javalang.tree.BlockStatement", "label": null, "statements": [{"py/object": "javalang.tree.StatementExpression", "label": null, "expression": {"py/object": "javalang.tree.Assignment", "expressionl": {"py/object": "javalang.tree.MemberReference", "prefix_operators": [], "postfix_operators": [], "qualifier": "", "selectors": [], "member": "sisaBagi", "_position": {"py/object": "javalang.tokenizer.Position", "py/newargs": {"py/tuple": [22, 13]}, "py/seq": [22, 13]}}, "value": {"py/object": "javalang.tree.BinaryOperation", "operator": "%", "operandl": {"py/object": "javalang.tree.MemberReference", "prefix_operators": [], "postfix_operators": [], "qualifier": "", "selectors": [], "member": "number", "_position": {"py/object": "javalang.tokenizer.Position", "py/newargs": {"py/tuple": [22, 24]}, "py/seq": [22, 24]}}, "operandr": {"py/object": "javalang.tree.Literal", "prefix_operators": [], "postfix_operators": [], "qualifier": null, "selectors": [], "value": "10", "_position": {"py/object": "javalang.tokenizer.Position", "py/newargs": {"py/tuple": [22, 33]}, "py/seq": [22, 33]}}}, "type": "="}, "_position": {"py/id": 99}}, {"py/object": "javalang.tree.StatementExpression", "label": null, "expression": {"py/object": "javalang.tree.MethodInvocation", "prefix_operators": [], "postfix_operators": [], "qualifier": "System.out", "selectors": [], "type_arguments": null, "arguments": [{"py/object": "javalang.tree.MemberReference", "prefix_operators": [], "postfix_operators": [], "qualifier": "", "selectors": [], "member": "sisaBagi", "_position": {"py/object": "javalang.tokenizer.Position", "py/newargs": {"py/tuple": [23, 30]}, "py/seq": [23, 30]}}], "member": "print", "_position": {"py/object": "javalang.tokenizer.Position", "py/newargs": {"py/tuple": [23, 13]}, "py/seq": [23, 13]}}, "_position": {"py/id": 122}}, {"py/object": "javalang.tree.StatementExpression", "label": null, "expression": {"py/object": "javalang.tree.Assignment", "expressionl": {"py/object": "javalang.tree.MemberReference", "prefix_operators": [], "postfix_operators": [], "qualifier": "", "selectors": [], "member": "number", "_position": {"py/object": "javalang.tokenizer.Position", "py/newargs": {"py/tuple": [24, 13]}, "py/seq": [24, 13]}}, "value": {"py/object": "javalang.tree.BinaryOperation", "operator": "/", "operandl": {"py/object": "javalang.tree.MemberReference", "prefix_operators": [], "postfix_operators": [], "qualifier": "", "selectors": [], "member": "number", "_position": {"py/object": "javalang.tokenizer.Position", "py/newargs": {"py/tuple": [24, 22]}, "py/seq": [24, 22]}}, "operandr": {"py/object": "javalang.tree.Literal", "prefix_operators": [], "postfix_operators": [], "qualifier": null, "selectors": [], "value": "10", "_position": {"py/object": "javalang.tokenizer.Position", "py/newargs": {"py/tuple": [24, 31]}, "py/seq": [24, 31]}}}, "type": "="}, "_position": {"py/id": 129}}], "_position": {"py/object": "javalang.tokenizer.Position", "py/newargs": {"py/tuple": [21, 29]}, "py/seq": [21, 29]}}, "_position": {"py/object": "javalang.tokenizer.Position", "py/newargs": {"py/tuple": [21, 9]}, "py/seq": [21, 9]}}, {"py/object": "javalang.tree.StatementExpression", "label": null, "expression": {"py/object": "javalang.tree.MethodInvocation", "prefix_operators": [], "postfix_operators": [], "qualifier": "System.out", "selectors": [], "type_arguments": null, "arguments": [], "member": "println", "_position": {"py/object": "javalang.tokenizer.Position", "py/newargs": {"py/tuple": [26, 9]}, "py/seq": [26, 9]}}, "_position": {"py/id": 149}}], "_position": {"py/object": "javalang.tokenizer.Position", "py/newargs": {"py/tuple": [13, 19]}, "py/seq": [13, 19]}}], "type_parameters": null, "extends": null, "implements": null, "_position": {"py/object": "javalang.tokenizer.Position", "py/newargs": {"py/tuple": [11, 8]}, "py/seq": [11, 8]}}]}